JS8CallAPI/__init__.py
JS8CallAPI/core.py
JS8CallAPI/grid_utils.py
backstop_python_js8call_api-0.1.1.dist-info/licenses/LICENSE
backstop_python_js8call_api-0.1.1.dist-info/METADATA
backstop_python_js8call_api-0.1.1.dist-info/WHEEL
backstop_python_js8call_api-0.1.1.dist-info/top_level.txt
backstop_python_js8call_api-0.1.1.dist-info/RECORD
