Metadata-Version: 2.4
Name: backstop-python-js8call-api
Version: 0.1.1
Summary: A Python library for interacting with JS8Call's TCP API, featuring GPS integration and automated grid square management.
Home-page: https://github.com/tirandagan/backstop-python-js8call-api
Author: Tiran Dagan
Author-email: tiran@backstopbeta.com
License: MIT
Classifier: Development Status :: 3 - Alpha
Classifier: Intended Audience :: Developers
Classifier: Operating System :: OS Independent
Classifier: Programming Language :: Python :: 3
Classifier: Programming Language :: Python :: 3.6
Classifier: Programming Language :: Python :: 3.7
Classifier: Programming Language :: Python :: 3.8
Classifier: Programming Language :: Python :: 3.9
Classifier: Topic :: Communications :: Ham Radio
Requires-Python: >=3.6
License-File: LICENSE
Requires-Dist: gpsd-py3==0.3.0
Dynamic: author
Dynamic: author-email
Dynamic: classifier
Dynamic: description
Dynamic: description-content-type
Dynamic: home-page
Dynamic: license
Dynamic: license-file
Dynamic: requires-dist
Dynamic: requires-python
Dynamic: summary
